pyrobotiqgripper/__init__.py
pyrobotiqgripper-1.0.1.dist-info/LICENSE
pyrobotiqgripper-1.0.1.dist-info/METADATA
pyrobotiqgripper-1.0.1.dist-info/WHEEL
pyrobotiqgripper-1.0.1.dist-info/RECORD
