Metadata-Version: 2.3
Name: pyrobotiqgripper
Version: 1.0.1
Summary: Python Driver for Robotiq Grippers via Modbus RTU
Author: Benoit CASTETS
Author-email: opensourceeng@gmail.com
Requires-Python: >=3.8.1,<4.0
Classifier: License :: OSI Approved :: MIT License
Classifier: Operating System :: OS Independent
Classifier: Programming Language :: Python :: 3
Classifier: Programming Language :: Python :: 3.9
Classifier: Programming Language :: Python :: 3.10
Classifier: Programming Language :: Python :: 3.11
Classifier: Programming Language :: Python :: 3.12
Classifier: Programming Language :: Python :: 3.13
Requires-Dist: minimalmodbus (>=2.1.1,<3.0.0)
Project-URL: Homepage, https://github.com/castetsb/pyRobotiqGripper
Project-URL: Issues, https://github.com/castetsb/pyRobotiqGripper/issues
